sutilybrary/__init__.py
sutilybrary/graph/__init__.py
sutilybrary/graph/graph_algorithms.py
sutilybrary/searching/__init__.py
sutilybrary/searching/searching_algorithms.py
sutilybrary/sorting/__init__.py
sutilybrary/sorting/sorting_algorithms.py
sutilybrary/string/__init__.py
sutilybrary/string/string_algorithms.py
sutilybrary/work_num/__init__.py
sutilybrary/work_num/work_num_algorithm.py
sutilibrary-2.1.3.dist-info/LICENSE
sutilibrary-2.1.3.dist-info/METADATA
sutilibrary-2.1.3.dist-info/WHEEL
sutilibrary-2.1.3.dist-info/entry_points.txt
sutilibrary-2.1.3.dist-info/top_level.txt
sutilibrary-2.1.3.dist-info/RECORD
